request_logger/__init__.py
request_logger/admin.py
request_logger/apps.py
request_logger/decorators.py
request_logger/management/__init__.py
request_logger/management/commands/__init__.py
request_logger/management/commands/truncate_request_logs.py
request_logger/migrations/0001_initial.py
request_logger/migrations/0002_alter_requestlog_response_class.py
request_logger/migrations/0003_requestlog_context.py
request_logger/migrations/__init__.py
request_logger/models.py
request_logger/settings.py
django_request_logger_2-0.5.0.dist-info/METADATA
django_request_logger_2-0.5.0.dist-info/WHEEL
django_request_logger_2-0.5.0.dist-info/licenses/LICENSE
django_request_logger_2-0.5.0.dist-info/RECORD
