Metadata-Version: 2.4
Name: django-request-logger-2
Version: 0.5.0
Summary: Django model for storing HttpRequest information.
License: MIT
License-File: LICENSE
Author: YunoJuno
Author-email: code@yunojuno.com
Maintainer: YunoJuno
Maintainer-email: code@yunojuno.com
Requires-Python: >=3.12,<4.0
Classifier: Development Status :: 4 - Beta
Classifier: Environment :: Web Environment
Classifier: Framework :: Django
Classifier: Framework :: Django :: 5.2
Classifier: Framework :: Django :: 6.0
Classifier: License :: OSI Approved :: MIT License
Classifier: Operating System :: OS Independent
Classifier: Programming Language :: Python :: 3
Classifier: Programming Language :: Python :: 3.12
Classifier: Programming Language :: Python :: 3.13
Classifier: Programming Language :: Python :: 3.14
Classifier: Programming Language :: Python :: 3 :: Only
Provides-Extra: demo
Requires-Dist: django (>=5.2,<7.0)
Requires-Dist: django-rest-framework ; extra == "demo"
Project-URL: Documentation, https://github.com/yunojuno/django-request-log
Project-URL: Homepage, https://github.com/yunojuno/django-request-log
Project-URL: Repository, https://github.com/yunojuno/django-request-log
